README.rst
setup.py
bull/__init__.py
bull/bull.py
bull/models.py
bull.egg-info/PKG-INFO
bull.egg-info/SOURCES.txt
bull.egg-info/dependency_links.txt
bull.egg-info/not-zip-safe
bull.egg-info/requires.txt
bull.egg-info/top_level.txt
scripts/bull
scripts/create_user.py