Metadata-Version: 1.1
Name: bull
Version: 0.4.1
Summary: Digital goods payment processing made simple
Home-page: http://github.com/jeffknupp/bull/
Author: Jeff Knupp
Author-email: jeff@jeffknupp.com
License: Apache Software License
Platform: any
Classifier: Programming Language :: Python
Classifier: Development Status :: 4 - Beta
Classifier: Natural Language :: English
Classifier: Environment :: Web Environment
Classifier: Intended Audience :: Developers
Classifier: License :: OSI Approved :: Apache Software License
Classifier: Operating System :: OS Independent
Classifier: Topic :: Software Development :: Libraries :: Python Modules
Classifier: Topic :: Software Development :: Libraries :: Application Frameworks
Classifier: Topic :: Internet :: WWW/HTTP :: Dynamic Content
